springerdl
