Metadata-Version: 1.0
Name: springerdl
Version: 1.3-dev
Summary: Download whole books from link.springer.com
Home-page: https://github.com/mbr/springerdownload
Author: Marc Brinkmann <git@marcbrinkmann.de>, Thomas Vogt <tuxor1337@web.de>
Author-email: git@marcbrinkmann.de
License: UNKNOWN
Platform: UNKNOWN
